{
  "cmd": "target/release/compress /Users/catwong/Desktop/zyzzyva/code/laps/experiments_iterative/outputs/domains/drawings_dials/stitch/seed_0/stitch_10/0/train/stitch_frontiers.json --out=/Users/catwong/Desktop/zyzzyva/code/laps/experiments_iterative/outputs/domains/drawings_dials/stitch/seed_0/stitch_10/0/train/stitch_output.json --max-arity=2 --iterations=10 --fmt=dreamcoder",
  "args": {
    "file": "/Users/catwong/Desktop/zyzzyva/code/laps/experiments_iterative/outputs/domains/drawings_dials/stitch/seed_0/stitch_10/0/train/stitch_frontiers.json",
    "out": "/Users/catwong/Desktop/zyzzyva/code/laps/experiments_iterative/outputs/domains/drawings_dials/stitch/seed_0/stitch_10/0/train/stitch_output.json",
    "iterations": 10,
    "shuffle": false,
    "truncate": null,
    "fmt": "Dreamcoder",
    "no_opt": false,
    "step": {
      "max_arity": 2,
      "threads": 1,
      "inv_candidates": 1,
      "hole_choice": "MinCost",
      "no_top_lambda": false,
      "track": null,
      "verbose_worklist": false,
      "verbose_best": false,
      "break_early_assignment": false,
      "fifo_worklist": false,
      "ascending_worklist": false,
      "lossy_candidates": false,
      "no_cache": false,
      "show_rewritten": false,
      "no_opt_free_vars": false,
      "no_opt_single_use": false,
      "no_opt_single_task": false,
      "no_opt_upper_bound": false,
      "no_opt_force_multiuse": false,
      "no_opt_useless_abstract": false,
      "no_stats": false,
      "no_other_util": false,
      "no_ctx_thread": false,
      "eta_long": false
    }
  },
  "original_cost": 102808,
  "original": [
    "(C (C (C (T (T (T l (M 3 (/ pi 2) 0 (- 0 2))) (M 1 0 0 0)) (M 1 0 0 0)) (T (T (T l (M 1 0 (- 0 0.5) 0)) (M (- (* 1 2) 0) 0 0 0)) (M 1 0 0 (- (* (* 0.5 1) 2) 0)))) (T (T c (M 1 0 (- 0 (+ 0.5 1)) (* 0.5 1))) (M 1 0 0 (* 0.5 1)))) (T (T c (M 1 0 (+ 0.5 1) (* 0.5 1))) (M 1 0 0 (* 0.5 1))))",
    "(C (C (C (T (T (T l (M 3 (/ pi 2) 0 (- 0 2))) (M 1 0 0 0)) (M 1 0 0 0)) (T (T (T l (M 1 0 (- 0 0.5) 0)) (M (- (* 1 2) 0) 0 0 0)) (M 1 0 0 (- (* (* 0.5 1) 2) 0)))) (T (T r (M 1 0 (- 0 (+ 0.5 1)) (* 0.5 1))) (M 1 0 0 (* 0.5 1)))) (T (T r (M 1 0 (+ 0.5 1) (* 0.5 1))) (M 1 0 0 (* 0.5 1))))",
    "(C (T (T (T l (M 3 (/ pi 2) 0 (- 0 2))) (M 1 0 0 0)) (M 1 0 0 0)) (T (T (T l (M 1 0 (- 0 0.5) 0)) (M (* 1 2) 0 0 0)) (M 1 0 0 (- (* (* 0.5 1) 2) 0))))",
    "(C (C (C (T (T (T l (M 3 (/ pi 2) 0 (- 0 2))) (M 1 0 0 0)) (M 1 0 0 0)) (T (T (T l (M 1 0 (- 0 0.5) 0)) (M (* 1 2) 0 0 0)) (M 1 0 0 (- (* (* 0.5 1) 2) 0)))) (T (T c (M 1 0 (- 0 (+ 0.5 1)) (* 0.5 1))) (M 1 0 0 (* 0.5 1)))) (T (T c (M 1 0 (+ 0.5 1) (* 0.5 1))) (M 1 0 0 (* 0.5 1))))",
    "(C (C (C (T (T (T l (M 3 (/ pi 2) 0 (- 0 2))) (M 1 0 0 0)) (M 1 0 0 0)) (T (T (T l (M 1 0 (- 0 0.5) 0)) (M (* 1 2) 0 0 0)) (M 1 0 0 (- (* (* 0.5 1) 2) 0)))) (T (T r (M 1 0 (- 0 (+ 0.5 1)) (* 0.5 1))) (M 1 0 0 (* 0.5 1)))) (T (T r (M 1 0 (+ 0.5 1) (* 0.5 1))) (M 1 0 0 (* 0.5 1))))",
    "(C (C (C (C (T (T (T l (M 3 (/ pi 2) 0 (- 0 2))) (M 1 0 0 0)) (M 1 0 0 0)) (T (T (T l (M 1 0 (- 0 0.5) 0)) (M (- (* 1 2) 0) 0 0 0)) (M 1 0 0 (- (* (* 0.5 1) 2) 0)))) (T (T (T l (M 1 0 (- 0 0.5) 0)) (M (- (* 1 2) 1) 0 0 0)) (M 1 0 0 (- (* (* 0.5 1) 2) 1)))) (T (T c (M 1 0 (- 0 (+ 0.5 1)) (* 0.5 1))) (M 1 0 0 (* 0.5 1)))) (T (T c (M 1 0 (+ 0.5 1) (* 0.5 1))) (M 1 0 0 (* 0.5 1))))",
    "(C (C (T (T (T l (M 3 (/ pi 2) 0 (- 0 2))) (M 1 0 0 0)) (M 1 0 0 0)) (T (T (T l (M 1 0 (- 0 0.5) 0)) (M (* 1 2) 0 0 0)) (M 1 0 0 (- (* (* 0.5 1) 2) 0)))) (T (T (T l (M 1 0 (- 0 0.5) 0)) (M (* 1 2) 0 0 0)) (M 1 0 0 (- (* (* 0.5 1) 2) 1))))",
    "(C (C (C (C (T (T (T l (M 3 (/ pi 2) 0 (- 0 2))) (M 1 0 0 0)) (M 1 0 0 0)) (T (T (T l (M 1 0 (- 0 0.5) 0)) (M (* 1 2) 0 0 0)) (M 1 0 0 (- (* (* 0.5 1) 2) 0)))) (T (T (T l (M 1 0 (- 0 0.5) 0)) (M (* 1 2) 0 0 0)) (M 1 0 0 (- (* (* 0.5 1) 2) 1)))) (T (T c (M 1 0 (- 0 (+ 0.5 1)) (* 0.5 1))) (M 1 0 0 (* 0.5 1)))) (T (T c (M 1 0 (+ 0.5 1) (* 0.5 1))) (M 1 0 0 (* 0.5 1))))",
    "(C (C (C (C (T (T (T l (M 3 (/ pi 2) 0 (- 0 2))) (M 1 0 0 0)) (M 1 0 0 0)) (T (T (T l (M 1 0 (- 0 0.5) 0)) (M (* 1 2) 0 0 0)) (M 1 0 0 (- (* (* 0.5 1) 2) 0)))) (T (T (T l (M 1 0 (- 0 0.5) 0)) (M (* 1 2) 0 0 0)) (M 1 0 0 (- (* (* 0.5 1) 2) 1)))) (T (T r (M 1 0 (- 0 (+ 0.5 1)) (* 0.5 1))) (M 1 0 0 (* 0.5 1)))) (T (T r (M 1 0 (+ 0.5 1) (* 0.5 1))) (M 1 0 0 (* 0.5 1))))",
    "(C (C (C (T (T (T l (M 3 (/ pi 2) 0 (- 0 2))) (M 1 0 0 0)) (M 1 0 0 0)) (T (T (T l (M 1 0 (- 0 0.5) 0)) (M (- (* 1 2) 0) 0 0 0)) (M 1 0 0 (- (* (* 0.5 1) 2) 0)))) (T (T (T l (M 1 0 (- 0 0.5) 0)) (M (- (* 1 2) 1) 0 0 0)) (M 1 0 0 (- (* (* 0.5 1) 2) 1)))) (T (T (T l (M 1 0 (- 0 0.5) 0)) (M (- (* 1 2) 2) 0 0 0)) (M 1 0 0 (- (* (* 0.5 1) 2) 2))))"
  ],
  "invs": [
    {
      "body": "(C (T (T (T l (M 3 (/ pi 2) 0 (- 0 2))) (M 1 0 0 0)) (M 1 0 0 0)) (T (T (T l (M 1 0 (- 0 0.5) 0)) (M #0 0 0 0)) (M 1 0 0 (- (* (* 0.5 1) 2) 0))))",
      "dreamcoder": "#(lambda (C (T (T (T l (M 3 (/ pi 2) 0 (- 0 2))) (M 1 0 0 0)) (M 1 0 0 0)) (T (T (T l (M 1 0 (- 0 0.5) 0)) (M $0 0 0 0)) (M 1 0 0 (- (* (* 0.5 1) 2) 0)))))",
      "arity": 1,
      "name": "fn_0",
      "rewritten": [
        "(C (C (fn_0 (- (* 1 2) 0)) (T (T c (M 1 0 (- 0 (+ 0.5 1)) (* 0.5 1))) (M 1 0 0 (* 0.5 1)))) (T (T c (M 1 0 (+ 0.5 1) (* 0.5 1))) (M 1 0 0 (* 0.5 1))))",
        "(C (C (fn_0 (- (* 1 2) 0)) (T (T r (M 1 0 (- 0 (+ 0.5 1)) (* 0.5 1))) (M 1 0 0 (* 0.5 1)))) (T (T r (M 1 0 (+ 0.5 1) (* 0.5 1))) (M 1 0 0 (* 0.5 1))))",
        "(fn_0 (* 1 2))",
        "(C (C (fn_0 (* 1 2)) (T (T c (M 1 0 (- 0 (+ 0.5 1)) (* 0.5 1))) (M 1 0 0 (* 0.5 1)))) (T (T c (M 1 0 (+ 0.5 1) (* 0.5 1))) (M 1 0 0 (* 0.5 1))))",
        "(C (C (fn_0 (* 1 2)) (T (T r (M 1 0 (- 0 (+ 0.5 1)) (* 0.5 1))) (M 1 0 0 (* 0.5 1)))) (T (T r (M 1 0 (+ 0.5 1) (* 0.5 1))) (M 1 0 0 (* 0.5 1))))",
        "(C (C (C (fn_0 (- (* 1 2) 0)) (T (T (T l (M 1 0 (- 0 0.5) 0)) (M (- (* 1 2) 1) 0 0 0)) (M 1 0 0 (- (* (* 0.5 1) 2) 1)))) (T (T c (M 1 0 (- 0 (+ 0.5 1)) (* 0.5 1))) (M 1 0 0 (* 0.5 1)))) (T (T c (M 1 0 (+ 0.5 1) (* 0.5 1))) (M 1 0 0 (* 0.5 1))))",
        "(C (fn_0 (* 1 2)) (T (T (T l (M 1 0 (- 0 0.5) 0)) (M (* 1 2) 0 0 0)) (M 1 0 0 (- (* (* 0.5 1) 2) 1))))",
        "(C (C (C (fn_0 (* 1 2)) (T (T (T l (M 1 0 (- 0 0.5) 0)) (M (* 1 2) 0 0 0)) (M 1 0 0 (- (* (* 0.5 1) 2) 1)))) (T (T c (M 1 0 (- 0 (+ 0.5 1)) (* 0.5 1))) (M 1 0 0 (* 0.5 1)))) (T (T c (M 1 0 (+ 0.5 1) (* 0.5 1))) (M 1 0 0 (* 0.5 1))))",
        "(C (C (C (fn_0 (* 1 2)) (T (T (T l (M 1 0 (- 0 0.5) 0)) (M (* 1 2) 0 0 0)) (M 1 0 0 (- (* (* 0.5 1) 2) 1)))) (T (T r (M 1 0 (- 0 (+ 0.5 1)) (* 0.5 1))) (M 1 0 0 (* 0.5 1)))) (T (T r (M 1 0 (+ 0.5 1) (* 0.5 1))) (M 1 0 0 (* 0.5 1))))",
        "(C (C (fn_0 (- (* 1 2) 0)) (T (T (T l (M 1 0 (- 0 0.5) 0)) (M (- (* 1 2) 1) 0 0 0)) (M 1 0 0 (- (* (* 0.5 1) 2) 1)))) (T (T (T l (M 1 0 (- 0 0.5) 0)) (M (- (* 1 2) 2) 0 0 0)) (M 1 0 0 (- (* (* 0.5 1) 2) 2))))"
      ],
      "rewritten_dreamcoder": [
        "(C (C (#(lambda (C (T (T (T l (M 3 (/ pi 2) 0 (- 0 2))) (M 1 0 0 0)) (M 1 0 0 0)) (T (T (T l (M 1 0 (- 0 0.5) 0)) (M $0 0 0 0)) (M 1 0 0 (- (* (* 0.5 1) 2) 0))))) (- (* 1 2) 0)) (T (T c (M 1 0 (- 0 (+ 0.5 1)) (* 0.5 1))) (M 1 0 0 (* 0.5 1)))) (T (T c (M 1 0 (+ 0.5 1) (* 0.5 1))) (M 1 0 0 (* 0.5 1))))",
        "(C (C (#(lambda (C (T (T (T l (M 3 (/ pi 2) 0 (- 0 2))) (M 1 0 0 0)) (M 1 0 0 0)) (T (T (T l (M 1 0 (- 0 0.5) 0)) (M $0 0 0 0)) (M 1 0 0 (- (* (* 0.5 1) 2) 0))))) (- (* 1 2) 0)) (T (T r (M 1 0 (- 0 (+ 0.5 1)) (* 0.5 1))) (M 1 0 0 (* 0.5 1)))) (T (T r (M 1 0 (+ 0.5 1) (* 0.5 1))) (M 1 0 0 (* 0.5 1))))",
        "(#(lambda (C (T (T (T l (M 3 (/ pi 2) 0 (- 0 2))) (M 1 0 0 0)) (M 1 0 0 0)) (T (T (T l (M 1 0 (- 0 0.5) 0)) (M $0 0 0 0)) (M 1 0 0 (- (* (* 0.5 1) 2) 0))))) (* 1 2))",
        "(C (C (#(lambda (C (T (T (T l (M 3 (/ pi 2) 0 (- 0 2))) (M 1 0 0 0)) (M 1 0 0 0)) (T (T (T l (M 1 0 (- 0 0.5) 0)) (M $0 0 0 0)) (M 1 0 0 (- (* (* 0.5 1) 2) 0))))) (* 1 2)) (T (T c (M 1 0 (- 0 (+ 0.5 1)) (* 0.5 1))) (M 1 0 0 (* 0.5 1)))) (T (T c (M 1 0 (+ 0.5 1) (* 0.5 1))) (M 1 0 0 (* 0.5 1))))",
        "(C (C (#(lambda (C (T (T (T l (M 3 (/ pi 2) 0 (- 0 2))) (M 1 0 0 0)) (M 1 0 0 0)) (T (T (T l (M 1 0 (- 0 0.5) 0)) (M $0 0 0 0)) (M 1 0 0 (- (* (* 0.5 1) 2) 0))))) (* 1 2)) (T (T r (M 1 0 (- 0 (+ 0.5 1)) (* 0.5 1))) (M 1 0 0 (* 0.5 1)))) (T (T r (M 1 0 (+ 0.5 1) (* 0.5 1))) (M 1 0 0 (* 0.5 1))))",
        "(C (C (C (#(lambda (C (T (T (T l (M 3 (/ pi 2) 0 (- 0 2))) (M 1 0 0 0)) (M 1 0 0 0)) (T (T (T l (M 1 0 (- 0 0.5) 0)) (M $0 0 0 0)) (M 1 0 0 (- (* (* 0.5 1) 2) 0))))) (- (* 1 2) 0)) (T (T (T l (M 1 0 (- 0 0.5) 0)) (M (- (* 1 2) 1) 0 0 0)) (M 1 0 0 (- (* (* 0.5 1) 2) 1)))) (T (T c (M 1 0 (- 0 (+ 0.5 1)) (* 0.5 1))) (M 1 0 0 (* 0.5 1)))) (T (T c (M 1 0 (+ 0.5 1) (* 0.5 1))) (M 1 0 0 (* 0.5 1))))",
        "(C (#(lambda (C (T (T (T l (M 3 (/ pi 2) 0 (- 0 2))) (M 1 0 0 0)) (M 1 0 0 0)) (T (T (T l (M 1 0 (- 0 0.5) 0)) (M $0 0 0 0)) (M 1 0 0 (- (* (* 0.5 1) 2) 0))))) (* 1 2)) (T (T (T l (M 1 0 (- 0 0.5) 0)) (M (* 1 2) 0 0 0)) (M 1 0 0 (- (* (* 0.5 1) 2) 1))))",
        "(C (C (C (#(lambda (C (T (T (T l (M 3 (/ pi 2) 0 (- 0 2))) (M 1 0 0 0)) (M 1 0 0 0)) (T (T (T l (M 1 0 (- 0 0.5) 0)) (M $0 0 0 0)) (M 1 0 0 (- (* (* 0.5 1) 2) 0))))) (* 1 2)) (T (T (T l (M 1 0 (- 0 0.5) 0)) (M (* 1 2) 0 0 0)) (M 1 0 0 (- (* (* 0.5 1) 2) 1)))) (T (T c (M 1 0 (- 0 (+ 0.5 1)) (* 0.5 1))) (M 1 0 0 (* 0.5 1)))) (T (T c (M 1 0 (+ 0.5 1) (* 0.5 1))) (M 1 0 0 (* 0.5 1))))",
        "(C (C (C (#(lambda (C (T (T (T l (M 3 (/ pi 2) 0 (- 0 2))) (M 1 0 0 0)) (M 1 0 0 0)) (T (T (T l (M 1 0 (- 0 0.5) 0)) (M $0 0 0 0)) (M 1 0 0 (- (* (* 0.5 1) 2) 0))))) (* 1 2)) (T (T (T l (M 1 0 (- 0 0.5) 0)) (M (* 1 2) 0 0 0)) (M 1 0 0 (- (* (* 0.5 1) 2) 1)))) (T (T r (M 1 0 (- 0 (+ 0.5 1)) (* 0.5 1))) (M 1 0 0 (* 0.5 1)))) (T (T r (M 1 0 (+ 0.5 1) (* 0.5 1))) (M 1 0 0 (* 0.5 1))))",
        "(C (C (#(lambda (C (T (T (T l (M 3 (/ pi 2) 0 (- 0 2))) (M 1 0 0 0)) (M 1 0 0 0)) (T (T (T l (M 1 0 (- 0 0.5) 0)) (M $0 0 0 0)) (M 1 0 0 (- (* (* 0.5 1) 2) 0))))) (- (* 1 2) 0)) (T (T (T l (M 1 0 (- 0 0.5) 0)) (M (- (* 1 2) 1) 0 0 0)) (M 1 0 0 (- (* (* 0.5 1) 2) 1)))) (T (T (T l (M 1 0 (- 0 0.5) 0)) (M (- (* 1 2) 2) 0 0 0)) (M 1 0 0 (- (* (* 0.5 1) 2) 2))))"
      ],
      "utility": 41915,
      "expected_cost": 53318,
      "final_cost": 53318,
      "multiplier": 1.9282043587531414,
      "multiplier_wrt_orig": 1.9282043587531414,
      "num_uses": 10,
      "uses": [
        {
          "fn_0 (* 1 2)": "(C (T (T (T l (M 3 (/ pi 2) 0 (- 0 2))) (M 1 0 0 0)) (M 1 0 0 0)) (T (T (T l (M 1 0 (- 0 0.5) 0)) (M (* 1 2) 0 0 0)) (M 1 0 0 (- (* (* 0.5 1) 2) 0))))"
        },
        {
          "fn_0 (- (* 1 2) 0)": "(C (T (T (T l (M 3 (/ pi 2) 0 (- 0 2))) (M 1 0 0 0)) (M 1 0 0 0)) (T (T (T l (M 1 0 (- 0 0.5) 0)) (M (- (* 1 2) 0) 0 0 0)) (M 1 0 0 (- (* (* 0.5 1) 2) 0))))"
        }
      ]
    },
    {
      "body": "(C (C #1 (T (T #0 (M 1 0 (- 0 (+ 0.5 1)) (* 0.5 1))) (M 1 0 0 (* 0.5 1)))) (T (T #0 (M 1 0 (+ 0.5 1) (* 0.5 1))) (M 1 0 0 (* 0.5 1))))",
      "dreamcoder": "#(lambda (lambda (C (C $0 (T (T $1 (M 1 0 (- 0 (+ 0.5 1)) (* 0.5 1))) (M 1 0 0 (* 0.5 1)))) (T (T $1 (M 1 0 (+ 0.5 1) (* 0.5 1))) (M 1 0 0 (* 0.5 1))))))",
      "arity": 2,
      "name": "fn_1",
      "rewritten": [
        "(fn_1 c (fn_0 (- (* 1 2) 0)))",
        "(fn_1 r (fn_0 (- (* 1 2) 0)))",
        "(fn_0 (* 1 2))",
        "(fn_1 c (fn_0 (* 1 2)))",
        "(fn_1 r (fn_0 (* 1 2)))",
        "(fn_1 c (C (fn_0 (- (* 1 2) 0)) (T (T (T l (M 1 0 (- 0 0.5) 0)) (M (- (* 1 2) 1) 0 0 0)) (M 1 0 0 (- (* (* 0.5 1) 2) 1)))))",
        "(C (fn_0 (* 1 2)) (T (T (T l (M 1 0 (- 0 0.5) 0)) (M (* 1 2) 0 0 0)) (M 1 0 0 (- (* (* 0.5 1) 2) 1))))",
        "(fn_1 c (C (fn_0 (* 1 2)) (T (T (T l (M 1 0 (- 0 0.5) 0)) (M (* 1 2) 0 0 0)) (M 1 0 0 (- (* (* 0.5 1) 2) 1)))))",
        "(fn_1 r (C (fn_0 (* 1 2)) (T (T (T l (M 1 0 (- 0 0.5) 0)) (M (* 1 2) 0 0 0)) (M 1 0 0 (- (* (* 0.5 1) 2) 1)))))",
        "(C (C (fn_0 (- (* 1 2) 0)) (T (T (T l (M 1 0 (- 0 0.5) 0)) (M (- (* 1 2) 1) 0 0 0)) (M 1 0 0 (- (* (* 0.5 1) 2) 1)))) (T (T (T l (M 1 0 (- 0 0.5) 0)) (M (- (* 1 2) 2) 0 0 0)) (M 1 0 0 (- (* (* 0.5 1) 2) 2))))"
      ],
      "rewritten_dreamcoder": [
        "(#(lambda (lambda (C (C $0 (T (T $1 (M 1 0 (- 0 (+ 0.5 1)) (* 0.5 1))) (M 1 0 0 (* 0.5 1)))) (T (T $1 (M 1 0 (+ 0.5 1) (* 0.5 1))) (M 1 0 0 (* 0.5 1)))))) c (#(lambda (C (T (T (T l (M 3 (/ pi 2) 0 (- 0 2))) (M 1 0 0 0)) (M 1 0 0 0)) (T (T (T l (M 1 0 (- 0 0.5) 0)) (M $0 0 0 0)) (M 1 0 0 (- (* (* 0.5 1) 2) 0))))) (- (* 1 2) 0)))",
        "(#(lambda (lambda (C (C $0 (T (T $1 (M 1 0 (- 0 (+ 0.5 1)) (* 0.5 1))) (M 1 0 0 (* 0.5 1)))) (T (T $1 (M 1 0 (+ 0.5 1) (* 0.5 1))) (M 1 0 0 (* 0.5 1)))))) r (#(lambda (C (T (T (T l (M 3 (/ pi 2) 0 (- 0 2))) (M 1 0 0 0)) (M 1 0 0 0)) (T (T (T l (M 1 0 (- 0 0.5) 0)) (M $0 0 0 0)) (M 1 0 0 (- (* (* 0.5 1) 2) 0))))) (- (* 1 2) 0)))",
        "(#(lambda (C (T (T (T l (M 3 (/ pi 2) 0 (- 0 2))) (M 1 0 0 0)) (M 1 0 0 0)) (T (T (T l (M 1 0 (- 0 0.5) 0)) (M $0 0 0 0)) (M 1 0 0 (- (* (* 0.5 1) 2) 0))))) (* 1 2))",
        "(#(lambda (lambda (C (C $0 (T (T $1 (M 1 0 (- 0 (+ 0.5 1)) (* 0.5 1))) (M 1 0 0 (* 0.5 1)))) (T (T $1 (M 1 0 (+ 0.5 1) (* 0.5 1))) (M 1 0 0 (* 0.5 1)))))) c (#(lambda (C (T (T (T l (M 3 (/ pi 2) 0 (- 0 2))) (M 1 0 0 0)) (M 1 0 0 0)) (T (T (T l (M 1 0 (- 0 0.5) 0)) (M $0 0 0 0)) (M 1 0 0 (- (* (* 0.5 1) 2) 0))))) (* 1 2)))",
        "(#(lambda (lambda (C (C $0 (T (T $1 (M 1 0 (- 0 (+ 0.5 1)) (* 0.5 1))) (M 1 0 0 (* 0.5 1)))) (T (T $1 (M 1 0 (+ 0.5 1) (* 0.5 1))) (M 1 0 0 (* 0.5 1)))))) r (#(lambda (C (T (T (T l (M 3 (/ pi 2) 0 (- 0 2))) (M 1 0 0 0)) (M 1 0 0 0)) (T (T (T l (M 1 0 (- 0 0.5) 0)) (M $0 0 0 0)) (M 1 0 0 (- (* (* 0.5 1) 2) 0))))) (* 1 2)))",
        "(#(lambda (lambda (C (C $0 (T (T $1 (M 1 0 (- 0 (+ 0.5 1)) (* 0.5 1))) (M 1 0 0 (* 0.5 1)))) (T (T $1 (M 1 0 (+ 0.5 1) (* 0.5 1))) (M 1 0 0 (* 0.5 1)))))) c (C (#(lambda (C (T (T (T l (M 3 (/ pi 2) 0 (- 0 2))) (M 1 0 0 0)) (M 1 0 0 0)) (T (T (T l (M 1 0 (- 0 0.5) 0)) (M $0 0 0 0)) (M 1 0 0 (- (* (* 0.5 1) 2) 0))))) (- (* 1 2) 0)) (T (T (T l (M 1 0 (- 0 0.5) 0)) (M (- (* 1 2) 1) 0 0 0)) (M 1 0 0 (- (* (* 0.5 1) 2) 1)))))",
        "(C (#(lambda (C (T (T (T l (M 3 (/ pi 2) 0 (- 0 2))) (M 1 0 0 0)) (M 1 0 0 0)) (T (T (T l (M 1 0 (- 0 0.5) 0)) (M $0 0 0 0)) (M 1 0 0 (- (* (* 0.5 1) 2) 0))))) (* 1 2)) (T (T (T l (M 1 0 (- 0 0.5) 0)) (M (* 1 2) 0 0 0)) (M 1 0 0 (- (* (* 0.5 1) 2) 1))))",
        "(#(lambda (lambda (C (C $0 (T (T $1 (M 1 0 (- 0 (+ 0.5 1)) (* 0.5 1))) (M 1 0 0 (* 0.5 1)))) (T (T $1 (M 1 0 (+ 0.5 1) (* 0.5 1))) (M 1 0 0 (* 0.5 1)))))) c (C (#(lambda (C (T (T (T l (M 3 (/ pi 2) 0 (- 0 2))) (M 1 0 0 0)) (M 1 0 0 0)) (T (T (T l (M 1 0 (- 0 0.5) 0)) (M $0 0 0 0)) (M 1 0 0 (- (* (* 0.5 1) 2) 0))))) (* 1 2)) (T (T (T l (M 1 0 (- 0 0.5) 0)) (M (* 1 2) 0 0 0)) (M 1 0 0 (- (* (* 0.5 1) 2) 1)))))",
        "(#(lambda (lambda (C (C $0 (T (T $1 (M 1 0 (- 0 (+ 0.5 1)) (* 0.5 1))) (M 1 0 0 (* 0.5 1)))) (T (T $1 (M 1 0 (+ 0.5 1) (* 0.5 1))) (M 1 0 0 (* 0.5 1)))))) r (C (#(lambda (C (T (T (T l (M 3 (/ pi 2) 0 (- 0 2))) (M 1 0 0 0)) (M 1 0 0 0)) (T (T (T l (M 1 0 (- 0 0.5) 0)) (M $0 0 0 0)) (M 1 0 0 (- (* (* 0.5 1) 2) 0))))) (* 1 2)) (T (T (T l (M 1 0 (- 0 0.5) 0)) (M (* 1 2) 0 0 0)) (M 1 0 0 (- (* (* 0.5 1) 2) 1)))))",
        "(C (C (#(lambda (C (T (T (T l (M 3 (/ pi 2) 0 (- 0 2))) (M 1 0 0 0)) (M 1 0 0 0)) (T (T (T l (M 1 0 (- 0 0.5) 0)) (M $0 0 0 0)) (M 1 0 0 (- (* (* 0.5 1) 2) 0))))) (- (* 1 2) 0)) (T (T (T l (M 1 0 (- 0 0.5) 0)) (M (- (* 1 2) 1) 0 0 0)) (M 1 0 0 (- (* (* 0.5 1) 2) 1)))) (T (T (T l (M 1 0 (- 0 0.5) 0)) (M (- (* 1 2) 2) 0 0 0)) (M 1 0 0 (- (* (* 0.5 1) 2) 2))))"
      ],
      "utility": 22217,
      "expected_cost": 25038,
      "final_cost": 25038,
      "multiplier": 2.129483185557952,
      "multiplier_wrt_orig": 4.106078760284368,
      "num_uses": 7,
      "uses": [
        {
          "fn_1 c (C (fn_0 (* 1 2)) (T (T (T l (M 1 0 (- 0 0.5) 0)) (M (* 1 2) 0 0 0)) (M 1 0 0 (- (* (* 0.5 1) 2) 1))))": "(C (C (C (fn_0 (* 1 2)) (T (T (T l (M 1 0 (- 0 0.5) 0)) (M (* 1 2) 0 0 0)) (M 1 0 0 (- (* (* 0.5 1) 2) 1)))) (T (T c (M 1 0 (- 0 (+ 0.5 1)) (* 0.5 1))) (M 1 0 0 (* 0.5 1)))) (T (T c (M 1 0 (+ 0.5 1) (* 0.5 1))) (M 1 0 0 (* 0.5 1))))"
        },
        {
          "fn_1 r (C (fn_0 (* 1 2)) (T (T (T l (M 1 0 (- 0 0.5) 0)) (M (* 1 2) 0 0 0)) (M 1 0 0 (- (* (* 0.5 1) 2) 1))))": "(C (C (C (fn_0 (* 1 2)) (T (T (T l (M 1 0 (- 0 0.5) 0)) (M (* 1 2) 0 0 0)) (M 1 0 0 (- (* (* 0.5 1) 2) 1)))) (T (T r (M 1 0 (- 0 (+ 0.5 1)) (* 0.5 1))) (M 1 0 0 (* 0.5 1)))) (T (T r (M 1 0 (+ 0.5 1) (* 0.5 1))) (M 1 0 0 (* 0.5 1))))"
        },
        {
          "fn_1 c (C (fn_0 (- (* 1 2) 0)) (T (T (T l (M 1 0 (- 0 0.5) 0)) (M (- (* 1 2) 1) 0 0 0)) (M 1 0 0 (- (* (* 0.5 1) 2) 1))))": "(C (C (C (fn_0 (- (* 1 2) 0)) (T (T (T l (M 1 0 (- 0 0.5) 0)) (M (- (* 1 2) 1) 0 0 0)) (M 1 0 0 (- (* (* 0.5 1) 2) 1)))) (T (T c (M 1 0 (- 0 (+ 0.5 1)) (* 0.5 1))) (M 1 0 0 (* 0.5 1)))) (T (T c (M 1 0 (+ 0.5 1) (* 0.5 1))) (M 1 0 0 (* 0.5 1))))"
        },
        {
          "fn_1 c (fn_0 (* 1 2))": "(C (C (fn_0 (* 1 2)) (T (T c (M 1 0 (- 0 (+ 0.5 1)) (* 0.5 1))) (M 1 0 0 (* 0.5 1)))) (T (T c (M 1 0 (+ 0.5 1) (* 0.5 1))) (M 1 0 0 (* 0.5 1))))"
        },
        {
          "fn_1 r (fn_0 (* 1 2))": "(C (C (fn_0 (* 1 2)) (T (T r (M 1 0 (- 0 (+ 0.5 1)) (* 0.5 1))) (M 1 0 0 (* 0.5 1)))) (T (T r (M 1 0 (+ 0.5 1) (* 0.5 1))) (M 1 0 0 (* 0.5 1))))"
        },
        {
          "fn_1 c (fn_0 (- (* 1 2) 0))": "(C (C (fn_0 (- (* 1 2) 0)) (T (T c (M 1 0 (- 0 (+ 0.5 1)) (* 0.5 1))) (M 1 0 0 (* 0.5 1)))) (T (T c (M 1 0 (+ 0.5 1) (* 0.5 1))) (M 1 0 0 (* 0.5 1))))"
        },
        {
          "fn_1 r (fn_0 (- (* 1 2) 0))": "(C (C (fn_0 (- (* 1 2) 0)) (T (T r (M 1 0 (- 0 (+ 0.5 1)) (* 0.5 1))) (M 1 0 0 (* 0.5 1)))) (T (T r (M 1 0 (+ 0.5 1) (* 0.5 1))) (M 1 0 0 (* 0.5 1))))"
        }
      ]
    },
    {
      "body": "(T (T (T l (M 1 0 (- 0 0.5) 0)) (M #1 0 0 0)) (M 1 0 0 (- (* (* 0.5 1) 2) #0)))",
      "dreamcoder": "#(lambda (lambda (T (T (T l (M 1 0 (- 0 0.5) 0)) (M $0 0 0 0)) (M 1 0 0 (- (* (* 0.5 1) 2) $1)))))",
      "arity": 2,
      "name": "fn_2",
      "rewritten": [
        "(fn_1 c (fn_0 (- (* 1 2) 0)))",
        "(fn_1 r (fn_0 (- (* 1 2) 0)))",
        "(fn_0 (* 1 2))",
        "(fn_1 c (fn_0 (* 1 2)))",
        "(fn_1 r (fn_0 (* 1 2)))",
        "(fn_1 c (C (fn_0 (- (* 1 2) 0)) (fn_2 1 (- (* 1 2) 1))))",
        "(C (fn_0 (* 1 2)) (fn_2 1 (* 1 2)))",
        "(fn_1 c (C (fn_0 (* 1 2)) (fn_2 1 (* 1 2))))",
        "(fn_1 r (C (fn_0 (* 1 2)) (fn_2 1 (* 1 2))))",
        "(C (C (fn_0 (- (* 1 2) 0)) (fn_2 1 (- (* 1 2) 1))) (fn_2 2 (- (* 1 2) 2)))"
      ],
      "rewritten_dreamcoder": [
        "(#(lambda (lambda (C (C $0 (T (T $1 (M 1 0 (- 0 (+ 0.5 1)) (* 0.5 1))) (M 1 0 0 (* 0.5 1)))) (T (T $1 (M 1 0 (+ 0.5 1) (* 0.5 1))) (M 1 0 0 (* 0.5 1)))))) c (#(lambda (C (T (T (T l (M 3 (/ pi 2) 0 (- 0 2))) (M 1 0 0 0)) (M 1 0 0 0)) (T (T (T l (M 1 0 (- 0 0.5) 0)) (M $0 0 0 0)) (M 1 0 0 (- (* (* 0.5 1) 2) 0))))) (- (* 1 2) 0)))",
        "(#(lambda (lambda (C (C $0 (T (T $1 (M 1 0 (- 0 (+ 0.5 1)) (* 0.5 1))) (M 1 0 0 (* 0.5 1)))) (T (T $1 (M 1 0 (+ 0.5 1) (* 0.5 1))) (M 1 0 0 (* 0.5 1)))))) r (#(lambda (C (T (T (T l (M 3 (/ pi 2) 0 (- 0 2))) (M 1 0 0 0)) (M 1 0 0 0)) (T (T (T l (M 1 0 (- 0 0.5) 0)) (M $0 0 0 0)) (M 1 0 0 (- (* (* 0.5 1) 2) 0))))) (- (* 1 2) 0)))",
        "(#(lambda (C (T (T (T l (M 3 (/ pi 2) 0 (- 0 2))) (M 1 0 0 0)) (M 1 0 0 0)) (T (T (T l (M 1 0 (- 0 0.5) 0)) (M $0 0 0 0)) (M 1 0 0 (- (* (* 0.5 1) 2) 0))))) (* 1 2))",
        "(#(lambda (lambda (C (C $0 (T (T $1 (M 1 0 (- 0 (+ 0.5 1)) (* 0.5 1))) (M 1 0 0 (* 0.5 1)))) (T (T $1 (M 1 0 (+ 0.5 1) (* 0.5 1))) (M 1 0 0 (* 0.5 1)))))) c (#(lambda (C (T (T (T l (M 3 (/ pi 2) 0 (- 0 2))) (M 1 0 0 0)) (M 1 0 0 0)) (T (T (T l (M 1 0 (- 0 0.5) 0)) (M $0 0 0 0)) (M 1 0 0 (- (* (* 0.5 1) 2) 0))))) (* 1 2)))",
        "(#(lambda (lambda (C (C $0 (T (T $1 (M 1 0 (- 0 (+ 0.5 1)) (* 0.5 1))) (M 1 0 0 (* 0.5 1)))) (T (T $1 (M 1 0 (+ 0.5 1) (* 0.5 1))) (M 1 0 0 (* 0.5 1)))))) r (#(lambda (C (T (T (T l (M 3 (/ pi 2) 0 (- 0 2))) (M 1 0 0 0)) (M 1 0 0 0)) (T (T (T l (M 1 0 (- 0 0.5) 0)) (M $0 0 0 0)) (M 1 0 0 (- (* (* 0.5 1) 2) 0))))) (* 1 2)))",
        "(#(lambda (lambda (C (C $0 (T (T $1 (M 1 0 (- 0 (+ 0.5 1)) (* 0.5 1))) (M 1 0 0 (* 0.5 1)))) (T (T $1 (M 1 0 (+ 0.5 1) (* 0.5 1))) (M 1 0 0 (* 0.5 1)))))) c (C (#(lambda (C (T (T (T l (M 3 (/ pi 2) 0 (- 0 2))) (M 1 0 0 0)) (M 1 0 0 0)) (T (T (T l (M 1 0 (- 0 0.5) 0)) (M $0 0 0 0)) (M 1 0 0 (- (* (* 0.5 1) 2) 0))))) (- (* 1 2) 0)) (#(lambda (lambda (T (T (T l (M 1 0 (- 0 0.5) 0)) (M $0 0 0 0)) (M 1 0 0 (- (* (* 0.5 1) 2) $1))))) 1 (- (* 1 2) 1))))",
        "(C (#(lambda (C (T (T (T l (M 3 (/ pi 2) 0 (- 0 2))) (M 1 0 0 0)) (M 1 0 0 0)) (T (T (T l (M 1 0 (- 0 0.5) 0)) (M $0 0 0 0)) (M 1 0 0 (- (* (* 0.5 1) 2) 0))))) (* 1 2)) (#(lambda (lambda (T (T (T l (M 1 0 (- 0 0.5) 0)) (M $0 0 0 0)) (M 1 0 0 (- (* (* 0.5 1) 2) $1))))) 1 (* 1 2)))",
        "(#(lambda (lambda (C (C $0 (T (T $1 (M 1 0 (- 0 (+ 0.5 1)) (* 0.5 1))) (M 1 0 0 (* 0.5 1)))) (T (T $1 (M 1 0 (+ 0.5 1) (* 0.5 1))) (M 1 0 0 (* 0.5 1)))))) c (C (#(lambda (C (T (T (T l (M 3 (/ pi 2) 0 (- 0 2))) (M 1 0 0 0)) (M 1 0 0 0)) (T (T (T l (M 1 0 (- 0 0.5) 0)) (M $0 0 0 0)) (M 1 0 0 (- (* (* 0.5 1) 2) 0))))) (* 1 2)) (#(lambda (lambda (T (T (T l (M 1 0 (- 0 0.5) 0)) (M $0 0 0 0)) (M 1 0 0 (- (* (* 0.5 1) 2) $1))))) 1 (* 1 2))))",
        "(#(lambda (lambda (C (C $0 (T (T $1 (M 1 0 (- 0 (+ 0.5 1)) (* 0.5 1))) (M 1 0 0 (* 0.5 1)))) (T (T $1 (M 1 0 (+ 0.5 1) (* 0.5 1))) (M 1 0 0 (* 0.5 1)))))) r (C (#(lambda (C (T (T (T l (M 3 (/ pi 2) 0 (- 0 2))) (M 1 0 0 0)) (M 1 0 0 0)) (T (T (T l (M 1 0 (- 0 0.5) 0)) (M $0 0 0 0)) (M 1 0 0 (- (* (* 0.5 1) 2) 0))))) (* 1 2)) (#(lambda (lambda (T (T (T l (M 1 0 (- 0 0.5) 0)) (M $0 0 0 0)) (M 1 0 0 (- (* (* 0.5 1) 2) $1))))) 1 (* 1 2))))",
        "(C (C (#(lambda (C (T (T (T l (M 3 (/ pi 2) 0 (- 0 2))) (M 1 0 0 0)) (M 1 0 0 0)) (T (T (T l (M 1 0 (- 0 0.5) 0)) (M $0 0 0 0)) (M 1 0 0 (- (* (* 0.5 1) 2) 0))))) (- (* 1 2) 0)) (#(lambda (lambda (T (T (T l (M 1 0 (- 0 0.5) 0)) (M $0 0 0 0)) (M 1 0 0 (- (* (* 0.5 1) 2) $1))))) 1 (- (* 1 2) 1))) (#(lambda (lambda (T (T (T l (M 1 0 (- 0 0.5) 0)) (M $0 0 0 0)) (M 1 0 0 (- (* (* 0.5 1) 2) $1))))) 2 (- (* 1 2) 2)))"
      ],
      "utility": 10755,
      "expected_cost": 10494,
      "final_cost": 10494,
      "multiplier": 2.3859348198970842,
      "multiplier_wrt_orig": 9.796836287402325,
      "num_uses": 6,
      "uses": [
        {
          "fn_2 1 (* 1 2)": "(T (T (T l (M 1 0 (- 0 0.5) 0)) (M (* 1 2) 0 0 0)) (M 1 0 0 (- (* (* 0.5 1) 2) 1)))"
        },
        {
          "fn_2 1 (- (* 1 2) 1)": "(T (T (T l (M 1 0 (- 0 0.5) 0)) (M (- (* 1 2) 1) 0 0 0)) (M 1 0 0 (- (* (* 0.5 1) 2) 1)))"
        },
        {
          "fn_2 2 (- (* 1 2) 2)": "(T (T (T l (M 1 0 (- 0 0.5) 0)) (M (- (* 1 2) 2) 0 0 0)) (M 1 0 0 (- (* (* 0.5 1) 2) 2)))"
        }
      ]
    },
    {
      "body": "(* 1 2)",
      "dreamcoder": "#(* 1 2)",
      "arity": 0,
      "name": "fn_3",
      "rewritten": [
        "(fn_1 c (fn_0 (- fn_3 0)))",
        "(fn_1 r (fn_0 (- fn_3 0)))",
        "(fn_0 fn_3)",
        "(fn_1 c (fn_0 fn_3))",
        "(fn_1 r (fn_0 fn_3))",
        "(fn_1 c (C (fn_0 (- fn_3 0)) (fn_2 1 (- fn_3 1))))",
        "(C (fn_0 fn_3) (fn_2 1 fn_3))",
        "(fn_1 c (C (fn_0 fn_3) (fn_2 1 fn_3)))",
        "(fn_1 r (C (fn_0 fn_3) (fn_2 1 fn_3)))",
        "(C (C (fn_0 (- fn_3 0)) (fn_2 1 (- fn_3 1))) (fn_2 2 (- fn_3 2)))"
      ],
      "rewritten_dreamcoder": [
        "(#(lambda (lambda (C (C $0 (T (T $1 (M 1 0 (- 0 (+ 0.5 1)) (* 0.5 1))) (M 1 0 0 (* 0.5 1)))) (T (T $1 (M 1 0 (+ 0.5 1) (* 0.5 1))) (M 1 0 0 (* 0.5 1)))))) c (#(lambda (C (T (T (T l (M 3 (/ pi 2) 0 (- 0 2))) (M 1 0 0 0)) (M 1 0 0 0)) (T (T (T l (M 1 0 (- 0 0.5) 0)) (M $0 0 0 0)) (M 1 0 0 (- (* (* 0.5 1) 2) 0))))) (- #(* 1 2) 0)))",
        "(#(lambda (lambda (C (C $0 (T (T $1 (M 1 0 (- 0 (+ 0.5 1)) (* 0.5 1))) (M 1 0 0 (* 0.5 1)))) (T (T $1 (M 1 0 (+ 0.5 1) (* 0.5 1))) (M 1 0 0 (* 0.5 1)))))) r (#(lambda (C (T (T (T l (M 3 (/ pi 2) 0 (- 0 2))) (M 1 0 0 0)) (M 1 0 0 0)) (T (T (T l (M 1 0 (- 0 0.5) 0)) (M $0 0 0 0)) (M 1 0 0 (- (* (* 0.5 1) 2) 0))))) (- #(* 1 2) 0)))",
        "(#(lambda (C (T (T (T l (M 3 (/ pi 2) 0 (- 0 2))) (M 1 0 0 0)) (M 1 0 0 0)) (T (T (T l (M 1 0 (- 0 0.5) 0)) (M $0 0 0 0)) (M 1 0 0 (- (* (* 0.5 1) 2) 0))))) #(* 1 2))",
        "(#(lambda (lambda (C (C $0 (T (T $1 (M 1 0 (- 0 (+ 0.5 1)) (* 0.5 1))) (M 1 0 0 (* 0.5 1)))) (T (T $1 (M 1 0 (+ 0.5 1) (* 0.5 1))) (M 1 0 0 (* 0.5 1)))))) c (#(lambda (C (T (T (T l (M 3 (/ pi 2) 0 (- 0 2))) (M 1 0 0 0)) (M 1 0 0 0)) (T (T (T l (M 1 0 (- 0 0.5) 0)) (M $0 0 0 0)) (M 1 0 0 (- (* (* 0.5 1) 2) 0))))) #(* 1 2)))",
        "(#(lambda (lambda (C (C $0 (T (T $1 (M 1 0 (- 0 (+ 0.5 1)) (* 0.5 1))) (M 1 0 0 (* 0.5 1)))) (T (T $1 (M 1 0 (+ 0.5 1) (* 0.5 1))) (M 1 0 0 (* 0.5 1)))))) r (#(lambda (C (T (T (T l (M 3 (/ pi 2) 0 (- 0 2))) (M 1 0 0 0)) (M 1 0 0 0)) (T (T (T l (M 1 0 (- 0 0.5) 0)) (M $0 0 0 0)) (M 1 0 0 (- (* (* 0.5 1) 2) 0))))) #(* 1 2)))",
        "(#(lambda (lambda (C (C $0 (T (T $1 (M 1 0 (- 0 (+ 0.5 1)) (* 0.5 1))) (M 1 0 0 (* 0.5 1)))) (T (T $1 (M 1 0 (+ 0.5 1) (* 0.5 1))) (M 1 0 0 (* 0.5 1)))))) c (C (#(lambda (C (T (T (T l (M 3 (/ pi 2) 0 (- 0 2))) (M 1 0 0 0)) (M 1 0 0 0)) (T (T (T l (M 1 0 (- 0 0.5) 0)) (M $0 0 0 0)) (M 1 0 0 (- (* (* 0.5 1) 2) 0))))) (- #(* 1 2) 0)) (#(lambda (lambda (T (T (T l (M 1 0 (- 0 0.5) 0)) (M $0 0 0 0)) (M 1 0 0 (- (* (* 0.5 1) 2) $1))))) 1 (- #(* 1 2) 1))))",
        "(C (#(lambda (C (T (T (T l (M 3 (/ pi 2) 0 (- 0 2))) (M 1 0 0 0)) (M 1 0 0 0)) (T (T (T l (M 1 0 (- 0 0.5) 0)) (M $0 0 0 0)) (M 1 0 0 (- (* (* 0.5 1) 2) 0))))) #(* 1 2)) (#(lambda (lambda (T (T (T l (M 1 0 (- 0 0.5) 0)) (M $0 0 0 0)) (M 1 0 0 (- (* (* 0.5 1) 2) $1))))) 1 #(* 1 2)))",
        "(#(lambda (lambda (C (C $0 (T (T $1 (M 1 0 (- 0 (+ 0.5 1)) (* 0.5 1))) (M 1 0 0 (* 0.5 1)))) (T (T $1 (M 1 0 (+ 0.5 1) (* 0.5 1))) (M 1 0 0 (* 0.5 1)))))) c (C (#(lambda (C (T (T (T l (M 3 (/ pi 2) 0 (- 0 2))) (M 1 0 0 0)) (M 1 0 0 0)) (T (T (T l (M 1 0 (- 0 0.5) 0)) (M $0 0 0 0)) (M 1 0 0 (- (* (* 0.5 1) 2) 0))))) #(* 1 2)) (#(lambda (lambda (T (T (T l (M 1 0 (- 0 0.5) 0)) (M $0 0 0 0)) (M 1 0 0 (- (* (* 0.5 1) 2) $1))))) 1 #(* 1 2))))",
        "(#(lambda (lambda (C (C $0 (T (T $1 (M 1 0 (- 0 (+ 0.5 1)) (* 0.5 1))) (M 1 0 0 (* 0.5 1)))) (T (T $1 (M 1 0 (+ 0.5 1) (* 0.5 1))) (M 1 0 0 (* 0.5 1)))))) r (C (#(lambda (C (T (T (T l (M 3 (/ pi 2) 0 (- 0 2))) (M 1 0 0 0)) (M 1 0 0 0)) (T (T (T l (M 1 0 (- 0 0.5) 0)) (M $0 0 0 0)) (M 1 0 0 (- (* (* 0.5 1) 2) 0))))) #(* 1 2)) (#(lambda (lambda (T (T (T l (M 1 0 (- 0 0.5) 0)) (M $0 0 0 0)) (M 1 0 0 (- (* (* 0.5 1) 2) $1))))) 1 #(* 1 2))))",
        "(C (C (#(lambda (C (T (T (T l (M 3 (/ pi 2) 0 (- 0 2))) (M 1 0 0 0)) (M 1 0 0 0)) (T (T (T l (M 1 0 (- 0 0.5) 0)) (M $0 0 0 0)) (M 1 0 0 (- (* (* 0.5 1) 2) 0))))) (- #(* 1 2) 0)) (#(lambda (lambda (T (T (T l (M 1 0 (- 0 0.5) 0)) (M $0 0 0 0)) (M 1 0 0 (- (* (* 0.5 1) 2) $1))))) 1 (- #(* 1 2) 1))) (#(lambda (lambda (T (T (T l (M 1 0 (- 0 0.5) 0)) (M $0 0 0 0)) (M 1 0 0 (- (* (* 0.5 1) 2) $1))))) 2 (- #(* 1 2) 2)))"
      ],
      "utility": 2779,
      "expected_cost": 7262,
      "final_cost": 7262,
      "multiplier": 1.445056458275957,
      "multiplier_wrt_orig": 14.15698154778298,
      "num_uses": 16,
      "uses": [
        {
          "fn_3 ": "(* 1 2)"
        }
      ]
    },
    {
      "body": "(C (fn_0 #1) (fn_2 1 #0))",
      "dreamcoder": "#(lambda (lambda (C (#(lambda (C (T (T (T l (M 3 (/ pi 2) 0 (- 0 2))) (M 1 0 0 0)) (M 1 0 0 0)) (T (T (T l (M 1 0 (- 0 0.5) 0)) (M $0 0 0 0)) (M 1 0 0 (- (* (* 0.5 1) 2) 0))))) $0) (#(lambda (lambda (T (T (T l (M 1 0 (- 0 0.5) 0)) (M $0 0 0 0)) (M 1 0 0 (- (* (* 0.5 1) 2) $1))))) 1 $1))))",
      "arity": 2,
      "name": "fn_4",
      "rewritten": [
        "(fn_1 c (fn_0 (- fn_3 0)))",
        "(fn_1 r (fn_0 (- fn_3 0)))",
        "(fn_0 fn_3)",
        "(fn_1 c (fn_0 fn_3))",
        "(fn_1 r (fn_0 fn_3))",
        "(fn_1 c (fn_4 (- fn_3 1) (- fn_3 0)))",
        "(fn_4 fn_3 fn_3)",
        "(fn_1 c (fn_4 fn_3 fn_3))",
        "(fn_1 r (fn_4 fn_3 fn_3))",
        "(C (fn_4 (- fn_3 1) (- fn_3 0)) (fn_2 2 (- fn_3 2)))"
      ],
      "rewritten_dreamcoder": [
        "(#(lambda (lambda (C (C $0 (T (T $1 (M 1 0 (- 0 (+ 0.5 1)) (* 0.5 1))) (M 1 0 0 (* 0.5 1)))) (T (T $1 (M 1 0 (+ 0.5 1) (* 0.5 1))) (M 1 0 0 (* 0.5 1)))))) c (#(lambda (C (T (T (T l (M 3 (/ pi 2) 0 (- 0 2))) (M 1 0 0 0)) (M 1 0 0 0)) (T (T (T l (M 1 0 (- 0 0.5) 0)) (M $0 0 0 0)) (M 1 0 0 (- (* (* 0.5 1) 2) 0))))) (- #(* 1 2) 0)))",
        "(#(lambda (lambda (C (C $0 (T (T $1 (M 1 0 (- 0 (+ 0.5 1)) (* 0.5 1))) (M 1 0 0 (* 0.5 1)))) (T (T $1 (M 1 0 (+ 0.5 1) (* 0.5 1))) (M 1 0 0 (* 0.5 1)))))) r (#(lambda (C (T (T (T l (M 3 (/ pi 2) 0 (- 0 2))) (M 1 0 0 0)) (M 1 0 0 0)) (T (T (T l (M 1 0 (- 0 0.5) 0)) (M $0 0 0 0)) (M 1 0 0 (- (* (* 0.5 1) 2) 0))))) (- #(* 1 2) 0)))",
        "(#(lambda (C (T (T (T l (M 3 (/ pi 2) 0 (- 0 2))) (M 1 0 0 0)) (M 1 0 0 0)) (T (T (T l (M 1 0 (- 0 0.5) 0)) (M $0 0 0 0)) (M 1 0 0 (- (* (* 0.5 1) 2) 0))))) #(* 1 2))",
        "(#(lambda (lambda (C (C $0 (T (T $1 (M 1 0 (- 0 (+ 0.5 1)) (* 0.5 1))) (M 1 0 0 (* 0.5 1)))) (T (T $1 (M 1 0 (+ 0.5 1) (* 0.5 1))) (M 1 0 0 (* 0.5 1)))))) c (#(lambda (C (T (T (T l (M 3 (/ pi 2) 0 (- 0 2))) (M 1 0 0 0)) (M 1 0 0 0)) (T (T (T l (M 1 0 (- 0 0.5) 0)) (M $0 0 0 0)) (M 1 0 0 (- (* (* 0.5 1) 2) 0))))) #(* 1 2)))",
        "(#(lambda (lambda (C (C $0 (T (T $1 (M 1 0 (- 0 (+ 0.5 1)) (* 0.5 1))) (M 1 0 0 (* 0.5 1)))) (T (T $1 (M 1 0 (+ 0.5 1) (* 0.5 1))) (M 1 0 0 (* 0.5 1)))))) r (#(lambda (C (T (T (T l (M 3 (/ pi 2) 0 (- 0 2))) (M 1 0 0 0)) (M 1 0 0 0)) (T (T (T l (M 1 0 (- 0 0.5) 0)) (M $0 0 0 0)) (M 1 0 0 (- (* (* 0.5 1) 2) 0))))) #(* 1 2)))",
        "(#(lambda (lambda (C (C $0 (T (T $1 (M 1 0 (- 0 (+ 0.5 1)) (* 0.5 1))) (M 1 0 0 (* 0.5 1)))) (T (T $1 (M 1 0 (+ 0.5 1) (* 0.5 1))) (M 1 0 0 (* 0.5 1)))))) c (#(lambda (lambda (C (#(lambda (C (T (T (T l (M 3 (/ pi 2) 0 (- 0 2))) (M 1 0 0 0)) (M 1 0 0 0)) (T (T (T l (M 1 0 (- 0 0.5) 0)) (M $0 0 0 0)) (M 1 0 0 (- (* (* 0.5 1) 2) 0))))) $0) (#(lambda (lambda (T (T (T l (M 1 0 (- 0 0.5) 0)) (M $0 0 0 0)) (M 1 0 0 (- (* (* 0.5 1) 2) $1))))) 1 $1)))) (- #(* 1 2) 1) (- #(* 1 2) 0)))",
        "(#(lambda (lambda (C (#(lambda (C (T (T (T l (M 3 (/ pi 2) 0 (- 0 2))) (M 1 0 0 0)) (M 1 0 0 0)) (T (T (T l (M 1 0 (- 0 0.5) 0)) (M $0 0 0 0)) (M 1 0 0 (- (* (* 0.5 1) 2) 0))))) $0) (#(lambda (lambda (T (T (T l (M 1 0 (- 0 0.5) 0)) (M $0 0 0 0)) (M 1 0 0 (- (* (* 0.5 1) 2) $1))))) 1 $1)))) #(* 1 2) #(* 1 2))",
        "(#(lambda (lambda (C (C $0 (T (T $1 (M 1 0 (- 0 (+ 0.5 1)) (* 0.5 1))) (M 1 0 0 (* 0.5 1)))) (T (T $1 (M 1 0 (+ 0.5 1) (* 0.5 1))) (M 1 0 0 (* 0.5 1)))))) c (#(lambda (lambda (C (#(lambda (C (T (T (T l (M 3 (/ pi 2) 0 (- 0 2))) (M 1 0 0 0)) (M 1 0 0 0)) (T (T (T l (M 1 0 (- 0 0.5) 0)) (M $0 0 0 0)) (M 1 0 0 (- (* (* 0.5 1) 2) 0))))) $0) (#(lambda (lambda (T (T (T l (M 1 0 (- 0 0.5) 0)) (M $0 0 0 0)) (M 1 0 0 (- (* (* 0.5 1) 2) $1))))) 1 $1)))) #(* 1 2) #(* 1 2)))",
        "(#(lambda (lambda (C (C $0 (T (T $1 (M 1 0 (- 0 (+ 0.5 1)) (* 0.5 1))) (M 1 0 0 (* 0.5 1)))) (T (T $1 (M 1 0 (+ 0.5 1) (* 0.5 1))) (M 1 0 0 (* 0.5 1)))))) r (#(lambda (lambda (C (#(lambda (C (T (T (T l (M 3 (/ pi 2) 0 (- 0 2))) (M 1 0 0 0)) (M 1 0 0 0)) (T (T (T l (M 1 0 (- 0 0.5) 0)) (M $0 0 0 0)) (M 1 0 0 (- (* (* 0.5 1) 2) 0))))) $0) (#(lambda (lambda (T (T (T l (M 1 0 (- 0 0.5) 0)) (M $0 0 0 0)) (M 1 0 0 (- (* (* 0.5 1) 2) $1))))) 1 $1)))) #(* 1 2) #(* 1 2)))",
        "(C (#(lambda (lambda (C (#(lambda (C (T (T (T l (M 3 (/ pi 2) 0 (- 0 2))) (M 1 0 0 0)) (M 1 0 0 0)) (T (T (T l (M 1 0 (- 0 0.5) 0)) (M $0 0 0 0)) (M 1 0 0 (- (* (* 0.5 1) 2) 0))))) $0) (#(lambda (lambda (T (T (T l (M 1 0 (- 0 0.5) 0)) (M $0 0 0 0)) (M 1 0 0 (- (* (* 0.5 1) 2) $1))))) 1 $1)))) (- #(* 1 2) 1) (- #(* 1 2) 0)) (#(lambda (lambda (T (T (T l (M 1 0 (- 0 0.5) 0)) (M $0 0 0 0)) (M 1 0 0 (- (* (* 0.5 1) 2) $1))))) 2 (- #(* 1 2) 2)))"
      ],
      "utility": 908,
      "expected_cost": 5747,
      "final_cost": 5747,
      "multiplier": 1.26361579954759,
      "multiplier_wrt_orig": 17.88898555768227,
      "num_uses": 5,
      "uses": [
        {
          "fn_4 (- fn_3 1) (- fn_3 0)": "(C (fn_0 (- fn_3 0)) (fn_2 1 (- fn_3 1)))"
        },
        {
          "fn_4 fn_3 fn_3": "(C (fn_0 fn_3) (fn_2 1 fn_3))"
        }
      ]
    },
    {
      "body": "(- fn_3)",
      "dreamcoder": "#(- #(* 1 2))",
      "arity": 0,
      "name": "fn_5",
      "rewritten": [
        "(fn_1 c (fn_0 (fn_5 0)))",
        "(fn_1 r (fn_0 (fn_5 0)))",
        "(fn_0 fn_3)",
        "(fn_1 c (fn_0 fn_3))",
        "(fn_1 r (fn_0 fn_3))",
        "(fn_1 c (fn_4 (fn_5 1) (fn_5 0)))",
        "(fn_4 fn_3 fn_3)",
        "(fn_1 c (fn_4 fn_3 fn_3))",
        "(fn_1 r (fn_4 fn_3 fn_3))",
        "(C (fn_4 (fn_5 1) (fn_5 0)) (fn_2 2 (fn_5 2)))"
      ],
      "rewritten_dreamcoder": [
        "(#(lambda (lambda (C (C $0 (T (T $1 (M 1 0 (- 0 (+ 0.5 1)) (* 0.5 1))) (M 1 0 0 (* 0.5 1)))) (T (T $1 (M 1 0 (+ 0.5 1) (* 0.5 1))) (M 1 0 0 (* 0.5 1)))))) c (#(lambda (C (T (T (T l (M 3 (/ pi 2) 0 (- 0 2))) (M 1 0 0 0)) (M 1 0 0 0)) (T (T (T l (M 1 0 (- 0 0.5) 0)) (M $0 0 0 0)) (M 1 0 0 (- (* (* 0.5 1) 2) 0))))) (#(- #(* 1 2)) 0)))",
        "(#(lambda (lambda (C (C $0 (T (T $1 (M 1 0 (- 0 (+ 0.5 1)) (* 0.5 1))) (M 1 0 0 (* 0.5 1)))) (T (T $1 (M 1 0 (+ 0.5 1) (* 0.5 1))) (M 1 0 0 (* 0.5 1)))))) r (#(lambda (C (T (T (T l (M 3 (/ pi 2) 0 (- 0 2))) (M 1 0 0 0)) (M 1 0 0 0)) (T (T (T l (M 1 0 (- 0 0.5) 0)) (M $0 0 0 0)) (M 1 0 0 (- (* (* 0.5 1) 2) 0))))) (#(- #(* 1 2)) 0)))",
        "(#(lambda (C (T (T (T l (M 3 (/ pi 2) 0 (- 0 2))) (M 1 0 0 0)) (M 1 0 0 0)) (T (T (T l (M 1 0 (- 0 0.5) 0)) (M $0 0 0 0)) (M 1 0 0 (- (* (* 0.5 1) 2) 0))))) #(* 1 2))",
        "(#(lambda (lambda (C (C $0 (T (T $1 (M 1 0 (- 0 (+ 0.5 1)) (* 0.5 1))) (M 1 0 0 (* 0.5 1)))) (T (T $1 (M 1 0 (+ 0.5 1) (* 0.5 1))) (M 1 0 0 (* 0.5 1)))))) c (#(lambda (C (T (T (T l (M 3 (/ pi 2) 0 (- 0 2))) (M 1 0 0 0)) (M 1 0 0 0)) (T (T (T l (M 1 0 (- 0 0.5) 0)) (M $0 0 0 0)) (M 1 0 0 (- (* (* 0.5 1) 2) 0))))) #(* 1 2)))",
        "(#(lambda (lambda (C (C $0 (T (T $1 (M 1 0 (- 0 (+ 0.5 1)) (* 0.5 1))) (M 1 0 0 (* 0.5 1)))) (T (T $1 (M 1 0 (+ 0.5 1) (* 0.5 1))) (M 1 0 0 (* 0.5 1)))))) r (#(lambda (C (T (T (T l (M 3 (/ pi 2) 0 (- 0 2))) (M 1 0 0 0)) (M 1 0 0 0)) (T (T (T l (M 1 0 (- 0 0.5) 0)) (M $0 0 0 0)) (M 1 0 0 (- (* (* 0.5 1) 2) 0))))) #(* 1 2)))",
        "(#(lambda (lambda (C (C $0 (T (T $1 (M 1 0 (- 0 (+ 0.5 1)) (* 0.5 1))) (M 1 0 0 (* 0.5 1)))) (T (T $1 (M 1 0 (+ 0.5 1) (* 0.5 1))) (M 1 0 0 (* 0.5 1)))))) c (#(lambda (lambda (C (#(lambda (C (T (T (T l (M 3 (/ pi 2) 0 (- 0 2))) (M 1 0 0 0)) (M 1 0 0 0)) (T (T (T l (M 1 0 (- 0 0.5) 0)) (M $0 0 0 0)) (M 1 0 0 (- (* (* 0.5 1) 2) 0))))) $0) (#(lambda (lambda (T (T (T l (M 1 0 (- 0 0.5) 0)) (M $0 0 0 0)) (M 1 0 0 (- (* (* 0.5 1) 2) $1))))) 1 $1)))) (#(- #(* 1 2)) 1) (#(- #(* 1 2)) 0)))",
        "(#(lambda (lambda (C (#(lambda (C (T (T (T l (M 3 (/ pi 2) 0 (- 0 2))) (M 1 0 0 0)) (M 1 0 0 0)) (T (T (T l (M 1 0 (- 0 0.5) 0)) (M $0 0 0 0)) (M 1 0 0 (- (* (* 0.5 1) 2) 0))))) $0) (#(lambda (lambda (T (T (T l (M 1 0 (- 0 0.5) 0)) (M $0 0 0 0)) (M 1 0 0 (- (* (* 0.5 1) 2) $1))))) 1 $1)))) #(* 1 2) #(* 1 2))",
        "(#(lambda (lambda (C (C $0 (T (T $1 (M 1 0 (- 0 (+ 0.5 1)) (* 0.5 1))) (M 1 0 0 (* 0.5 1)))) (T (T $1 (M 1 0 (+ 0.5 1) (* 0.5 1))) (M 1 0 0 (* 0.5 1)))))) c (#(lambda (lambda (C (#(lambda (C (T (T (T l (M 3 (/ pi 2) 0 (- 0 2))) (M 1 0 0 0)) (M 1 0 0 0)) (T (T (T l (M 1 0 (- 0 0.5) 0)) (M $0 0 0 0)) (M 1 0 0 (- (* (* 0.5 1) 2) 0))))) $0) (#(lambda (lambda (T (T (T l (M 1 0 (- 0 0.5) 0)) (M $0 0 0 0)) (M 1 0 0 (- (* (* 0.5 1) 2) $1))))) 1 $1)))) #(* 1 2) #(* 1 2)))",
        "(#(lambda (lambda (C (C $0 (T (T $1 (M 1 0 (- 0 (+ 0.5 1)) (* 0.5 1))) (M 1 0 0 (* 0.5 1)))) (T (T $1 (M 1 0 (+ 0.5 1) (* 0.5 1))) (M 1 0 0 (* 0.5 1)))))) r (#(lambda (lambda (C (#(lambda (C (T (T (T l (M 3 (/ pi 2) 0 (- 0 2))) (M 1 0 0 0)) (M 1 0 0 0)) (T (T (T l (M 1 0 (- 0 0.5) 0)) (M $0 0 0 0)) (M 1 0 0 (- (* (* 0.5 1) 2) 0))))) $0) (#(lambda (lambda (T (T (T l (M 1 0 (- 0 0.5) 0)) (M $0 0 0 0)) (M 1 0 0 (- (* (* 0.5 1) 2) $1))))) 1 $1)))) #(* 1 2) #(* 1 2)))",
        "(C (#(lambda (lambda (C (#(lambda (C (T (T (T l (M 3 (/ pi 2) 0 (- 0 2))) (M 1 0 0 0)) (M 1 0 0 0)) (T (T (T l (M 1 0 (- 0 0.5) 0)) (M $0 0 0 0)) (M 1 0 0 (- (* (* 0.5 1) 2) 0))))) $0) (#(lambda (lambda (T (T (T l (M 1 0 (- 0 0.5) 0)) (M $0 0 0 0)) (M 1 0 0 (- (* (* 0.5 1) 2) $1))))) 1 $1)))) (#(- #(* 1 2)) 1) (#(- #(* 1 2)) 0)) (#(lambda (lambda (T (T (T l (M 1 0 (- 0 0.5) 0)) (M $0 0 0 0)) (M 1 0 0 (- (* (* 0.5 1) 2) $1))))) 2 (#(- #(* 1 2)) 2)))"
      ],
      "utility": 406,
      "expected_cost": 5040,
      "final_cost": 5040,
      "multiplier": 1.1402777777777777,
      "multiplier_wrt_orig": 20.3984126984127,
      "num_uses": 7,
      "uses": [
        {
          "fn_5 ": "(- fn_3)"
        }
      ]
    },
    {
      "body": "(fn_4 fn_3 fn_3)",
      "dreamcoder": "#(#(lambda (lambda (C (#(lambda (C (T (T (T l (M 3 (/ pi 2) 0 (- 0 2))) (M 1 0 0 0)) (M 1 0 0 0)) (T (T (T l (M 1 0 (- 0 0.5) 0)) (M $0 0 0 0)) (M 1 0 0 (- (* (* 0.5 1) 2) 0))))) $0) (#(lambda (lambda (T (T (T l (M 1 0 (- 0 0.5) 0)) (M $0 0 0 0)) (M 1 0 0 (- (* (* 0.5 1) 2) $1))))) 1 $1)))) #(* 1 2) #(* 1 2))",
      "arity": 0,
      "name": "fn_6",
      "rewritten": [
        "(fn_1 c (fn_0 (fn_5 0)))",
        "(fn_1 r (fn_0 (fn_5 0)))",
        "(fn_0 fn_3)",
        "(fn_1 c (fn_0 fn_3))",
        "(fn_1 r (fn_0 fn_3))",
        "(fn_1 c (fn_4 (fn_5 1) (fn_5 0)))",
        "fn_6",
        "(fn_1 c fn_6)",
        "(fn_1 r fn_6)",
        "(C (fn_4 (fn_5 1) (fn_5 0)) (fn_2 2 (fn_5 2)))"
      ],
      "rewritten_dreamcoder": [
        "(#(lambda (lambda (C (C $0 (T (T $1 (M 1 0 (- 0 (+ 0.5 1)) (* 0.5 1))) (M 1 0 0 (* 0.5 1)))) (T (T $1 (M 1 0 (+ 0.5 1) (* 0.5 1))) (M 1 0 0 (* 0.5 1)))))) c (#(lambda (C (T (T (T l (M 3 (/ pi 2) 0 (- 0 2))) (M 1 0 0 0)) (M 1 0 0 0)) (T (T (T l (M 1 0 (- 0 0.5) 0)) (M $0 0 0 0)) (M 1 0 0 (- (* (* 0.5 1) 2) 0))))) (#(- #(* 1 2)) 0)))",
        "(#(lambda (lambda (C (C $0 (T (T $1 (M 1 0 (- 0 (+ 0.5 1)) (* 0.5 1))) (M 1 0 0 (* 0.5 1)))) (T (T $1 (M 1 0 (+ 0.5 1) (* 0.5 1))) (M 1 0 0 (* 0.5 1)))))) r (#(lambda (C (T (T (T l (M 3 (/ pi 2) 0 (- 0 2))) (M 1 0 0 0)) (M 1 0 0 0)) (T (T (T l (M 1 0 (- 0 0.5) 0)) (M $0 0 0 0)) (M 1 0 0 (- (* (* 0.5 1) 2) 0))))) (#(- #(* 1 2)) 0)))",
        "(#(lambda (C (T (T (T l (M 3 (/ pi 2) 0 (- 0 2))) (M 1 0 0 0)) (M 1 0 0 0)) (T (T (T l (M 1 0 (- 0 0.5) 0)) (M $0 0 0 0)) (M 1 0 0 (- (* (* 0.5 1) 2) 0))))) #(* 1 2))",
        "(#(lambda (lambda (C (C $0 (T (T $1 (M 1 0 (- 0 (+ 0.5 1)) (* 0.5 1))) (M 1 0 0 (* 0.5 1)))) (T (T $1 (M 1 0 (+ 0.5 1) (* 0.5 1))) (M 1 0 0 (* 0.5 1)))))) c (#(lambda (C (T (T (T l (M 3 (/ pi 2) 0 (- 0 2))) (M 1 0 0 0)) (M 1 0 0 0)) (T (T (T l (M 1 0 (- 0 0.5) 0)) (M $0 0 0 0)) (M 1 0 0 (- (* (* 0.5 1) 2) 0))))) #(* 1 2)))",
        "(#(lambda (lambda (C (C $0 (T (T $1 (M 1 0 (- 0 (+ 0.5 1)) (* 0.5 1))) (M 1 0 0 (* 0.5 1)))) (T (T $1 (M 1 0 (+ 0.5 1) (* 0.5 1))) (M 1 0 0 (* 0.5 1)))))) r (#(lambda (C (T (T (T l (M 3 (/ pi 2) 0 (- 0 2))) (M 1 0 0 0)) (M 1 0 0 0)) (T (T (T l (M 1 0 (- 0 0.5) 0)) (M $0 0 0 0)) (M 1 0 0 (- (* (* 0.5 1) 2) 0))))) #(* 1 2)))",
        "(#(lambda (lambda (C (C $0 (T (T $1 (M 1 0 (- 0 (+ 0.5 1)) (* 0.5 1))) (M 1 0 0 (* 0.5 1)))) (T (T $1 (M 1 0 (+ 0.5 1) (* 0.5 1))) (M 1 0 0 (* 0.5 1)))))) c (#(lambda (lambda (C (#(lambda (C (T (T (T l (M 3 (/ pi 2) 0 (- 0 2))) (M 1 0 0 0)) (M 1 0 0 0)) (T (T (T l (M 1 0 (- 0 0.5) 0)) (M $0 0 0 0)) (M 1 0 0 (- (* (* 0.5 1) 2) 0))))) $0) (#(lambda (lambda (T (T (T l (M 1 0 (- 0 0.5) 0)) (M $0 0 0 0)) (M 1 0 0 (- (* (* 0.5 1) 2) $1))))) 1 $1)))) (#(- #(* 1 2)) 1) (#(- #(* 1 2)) 0)))",
        "#(#(lambda (lambda (C (#(lambda (C (T (T (T l (M 3 (/ pi 2) 0 (- 0 2))) (M 1 0 0 0)) (M 1 0 0 0)) (T (T (T l (M 1 0 (- 0 0.5) 0)) (M $0 0 0 0)) (M 1 0 0 (- (* (* 0.5 1) 2) 0))))) $0) (#(lambda (lambda (T (T (T l (M 1 0 (- 0 0.5) 0)) (M $0 0 0 0)) (M 1 0 0 (- (* (* 0.5 1) 2) $1))))) 1 $1)))) #(* 1 2) #(* 1 2))",
        "(#(lambda (lambda (C (C $0 (T (T $1 (M 1 0 (- 0 (+ 0.5 1)) (* 0.5 1))) (M 1 0 0 (* 0.5 1)))) (T (T $1 (M 1 0 (+ 0.5 1) (* 0.5 1))) (M 1 0 0 (* 0.5 1)))))) c #(#(lambda (lambda (C (#(lambda (C (T (T (T l (M 3 (/ pi 2) 0 (- 0 2))) (M 1 0 0 0)) (M 1 0 0 0)) (T (T (T l (M 1 0 (- 0 0.5) 0)) (M $0 0 0 0)) (M 1 0 0 (- (* (* 0.5 1) 2) 0))))) $0) (#(lambda (lambda (T (T (T l (M 1 0 (- 0 0.5) 0)) (M $0 0 0 0)) (M 1 0 0 (- (* (* 0.5 1) 2) $1))))) 1 $1)))) #(* 1 2) #(* 1 2)))",
        "(#(lambda (lambda (C (C $0 (T (T $1 (M 1 0 (- 0 (+ 0.5 1)) (* 0.5 1))) (M 1 0 0 (* 0.5 1)))) (T (T $1 (M 1 0 (+ 0.5 1) (* 0.5 1))) (M 1 0 0 (* 0.5 1)))))) r #(#(lambda (lambda (C (#(lambda (C (T (T (T l (M 3 (/ pi 2) 0 (- 0 2))) (M 1 0 0 0)) (M 1 0 0 0)) (T (T (T l (M 1 0 (- 0 0.5) 0)) (M $0 0 0 0)) (M 1 0 0 (- (* (* 0.5 1) 2) 0))))) $0) (#(lambda (lambda (T (T (T l (M 1 0 (- 0 0.5) 0)) (M $0 0 0 0)) (M 1 0 0 (- (* (* 0.5 1) 2) $1))))) 1 $1)))) #(* 1 2) #(* 1 2)))",
        "(C (#(lambda (lambda (C (#(lambda (C (T (T (T l (M 3 (/ pi 2) 0 (- 0 2))) (M 1 0 0 0)) (M 1 0 0 0)) (T (T (T l (M 1 0 (- 0 0.5) 0)) (M $0 0 0 0)) (M 1 0 0 (- (* (* 0.5 1) 2) 0))))) $0) (#(lambda (lambda (T (T (T l (M 1 0 (- 0 0.5) 0)) (M $0 0 0 0)) (M 1 0 0 (- (* (* 0.5 1) 2) $1))))) 1 $1)))) (#(- #(* 1 2)) 1) (#(- #(* 1 2)) 0)) (#(lambda (lambda (T (T (T l (M 1 0 (- 0 0.5) 0)) (M $0 0 0 0)) (M 1 0 0 (- (* (* 0.5 1) 2) $1))))) 2 (#(- #(* 1 2)) 2)))"
      ],
      "utility": 153,
      "expected_cost": 4434,
      "final_cost": 4434,
      "multiplier": 1.1366711772665765,
      "multiplier_wrt_orig": 23.186287776274245,
      "num_uses": 3,
      "uses": [
        {
          "fn_6 ": "(fn_4 fn_3 fn_3)"
        }
      ]
    },
    {
      "body": "(fn_1 #0 (#1 (fn_5 0)))",
      "dreamcoder": "#(lambda (lambda (#(lambda (lambda (C (C $0 (T (T $1 (M 1 0 (- 0 (+ 0.5 1)) (* 0.5 1))) (M 1 0 0 (* 0.5 1)))) (T (T $1 (M 1 0 (+ 0.5 1) (* 0.5 1))) (M 1 0 0 (* 0.5 1)))))) $1 ($0 (#(- #(* 1 2)) 0)))))",
      "arity": 2,
      "name": "fn_7",
      "rewritten": [
        "(fn_7 c fn_0)",
        "(fn_7 r fn_0)",
        "(fn_0 fn_3)",
        "(fn_1 c (fn_0 fn_3))",
        "(fn_1 r (fn_0 fn_3))",
        "(fn_7 c (fn_4 (fn_5 1)))",
        "fn_6",
        "(fn_1 c fn_6)",
        "(fn_1 r fn_6)",
        "(C (fn_4 (fn_5 1) (fn_5 0)) (fn_2 2 (fn_5 2)))"
      ],
      "rewritten_dreamcoder": [
        "(#(lambda (lambda (#(lambda (lambda (C (C $0 (T (T $1 (M 1 0 (- 0 (+ 0.5 1)) (* 0.5 1))) (M 1 0 0 (* 0.5 1)))) (T (T $1 (M 1 0 (+ 0.5 1) (* 0.5 1))) (M 1 0 0 (* 0.5 1)))))) $1 ($0 (#(- #(* 1 2)) 0))))) c #(lambda (C (T (T (T l (M 3 (/ pi 2) 0 (- 0 2))) (M 1 0 0 0)) (M 1 0 0 0)) (T (T (T l (M 1 0 (- 0 0.5) 0)) (M $0 0 0 0)) (M 1 0 0 (- (* (* 0.5 1) 2) 0))))))",
        "(#(lambda (lambda (#(lambda (lambda (C (C $0 (T (T $1 (M 1 0 (- 0 (+ 0.5 1)) (* 0.5 1))) (M 1 0 0 (* 0.5 1)))) (T (T $1 (M 1 0 (+ 0.5 1) (* 0.5 1))) (M 1 0 0 (* 0.5 1)))))) $1 ($0 (#(- #(* 1 2)) 0))))) r #(lambda (C (T (T (T l (M 3 (/ pi 2) 0 (- 0 2))) (M 1 0 0 0)) (M 1 0 0 0)) (T (T (T l (M 1 0 (- 0 0.5) 0)) (M $0 0 0 0)) (M 1 0 0 (- (* (* 0.5 1) 2) 0))))))",
        "(#(lambda (C (T (T (T l (M 3 (/ pi 2) 0 (- 0 2))) (M 1 0 0 0)) (M 1 0 0 0)) (T (T (T l (M 1 0 (- 0 0.5) 0)) (M $0 0 0 0)) (M 1 0 0 (- (* (* 0.5 1) 2) 0))))) #(* 1 2))",
        "(#(lambda (lambda (C (C $0 (T (T $1 (M 1 0 (- 0 (+ 0.5 1)) (* 0.5 1))) (M 1 0 0 (* 0.5 1)))) (T (T $1 (M 1 0 (+ 0.5 1) (* 0.5 1))) (M 1 0 0 (* 0.5 1)))))) c (#(lambda (C (T (T (T l (M 3 (/ pi 2) 0 (- 0 2))) (M 1 0 0 0)) (M 1 0 0 0)) (T (T (T l (M 1 0 (- 0 0.5) 0)) (M $0 0 0 0)) (M 1 0 0 (- (* (* 0.5 1) 2) 0))))) #(* 1 2)))",
        "(#(lambda (lambda (C (C $0 (T (T $1 (M 1 0 (- 0 (+ 0.5 1)) (* 0.5 1))) (M 1 0 0 (* 0.5 1)))) (T (T $1 (M 1 0 (+ 0.5 1) (* 0.5 1))) (M 1 0 0 (* 0.5 1)))))) r (#(lambda (C (T (T (T l (M 3 (/ pi 2) 0 (- 0 2))) (M 1 0 0 0)) (M 1 0 0 0)) (T (T (T l (M 1 0 (- 0 0.5) 0)) (M $0 0 0 0)) (M 1 0 0 (- (* (* 0.5 1) 2) 0))))) #(* 1 2)))",
        "(#(lambda (lambda (#(lambda (lambda (C (C $0 (T (T $1 (M 1 0 (- 0 (+ 0.5 1)) (* 0.5 1))) (M 1 0 0 (* 0.5 1)))) (T (T $1 (M 1 0 (+ 0.5 1) (* 0.5 1))) (M 1 0 0 (* 0.5 1)))))) $1 ($0 (#(- #(* 1 2)) 0))))) c (#(lambda (lambda (C (#(lambda (C (T (T (T l (M 3 (/ pi 2) 0 (- 0 2))) (M 1 0 0 0)) (M 1 0 0 0)) (T (T (T l (M 1 0 (- 0 0.5) 0)) (M $0 0 0 0)) (M 1 0 0 (- (* (* 0.5 1) 2) 0))))) $0) (#(lambda (lambda (T (T (T l (M 1 0 (- 0 0.5) 0)) (M $0 0 0 0)) (M 1 0 0 (- (* (* 0.5 1) 2) $1))))) 1 $1)))) (#(- #(* 1 2)) 1)))",
        "#(#(lambda (lambda (C (#(lambda (C (T (T (T l (M 3 (/ pi 2) 0 (- 0 2))) (M 1 0 0 0)) (M 1 0 0 0)) (T (T (T l (M 1 0 (- 0 0.5) 0)) (M $0 0 0 0)) (M 1 0 0 (- (* (* 0.5 1) 2) 0))))) $0) (#(lambda (lambda (T (T (T l (M 1 0 (- 0 0.5) 0)) (M $0 0 0 0)) (M 1 0 0 (- (* (* 0.5 1) 2) $1))))) 1 $1)))) #(* 1 2) #(* 1 2))",
        "(#(lambda (lambda (C (C $0 (T (T $1 (M 1 0 (- 0 (+ 0.5 1)) (* 0.5 1))) (M 1 0 0 (* 0.5 1)))) (T (T $1 (M 1 0 (+ 0.5 1) (* 0.5 1))) (M 1 0 0 (* 0.5 1)))))) c #(#(lambda (lambda (C (#(lambda (C (T (T (T l (M 3 (/ pi 2) 0 (- 0 2))) (M 1 0 0 0)) (M 1 0 0 0)) (T (T (T l (M 1 0 (- 0 0.5) 0)) (M $0 0 0 0)) (M 1 0 0 (- (* (* 0.5 1) 2) 0))))) $0) (#(lambda (lambda (T (T (T l (M 1 0 (- 0 0.5) 0)) (M $0 0 0 0)) (M 1 0 0 (- (* (* 0.5 1) 2) $1))))) 1 $1)))) #(* 1 2) #(* 1 2)))",
        "(#(lambda (lambda (C (C $0 (T (T $1 (M 1 0 (- 0 (+ 0.5 1)) (* 0.5 1))) (M 1 0 0 (* 0.5 1)))) (T (T $1 (M 1 0 (+ 0.5 1) (* 0.5 1))) (M 1 0 0 (* 0.5 1)))))) r #(#(lambda (lambda (C (#(lambda (C (T (T (T l (M 3 (/ pi 2) 0 (- 0 2))) (M 1 0 0 0)) (M 1 0 0 0)) (T (T (T l (M 1 0 (- 0 0.5) 0)) (M $0 0 0 0)) (M 1 0 0 (- (* (* 0.5 1) 2) 0))))) $0) (#(lambda (lambda (T (T (T l (M 1 0 (- 0 0.5) 0)) (M $0 0 0 0)) (M 1 0 0 (- (* (* 0.5 1) 2) $1))))) 1 $1)))) #(* 1 2) #(* 1 2)))",
        "(C (#(lambda (lambda (C (#(lambda (C (T (T (T l (M 3 (/ pi 2) 0 (- 0 2))) (M 1 0 0 0)) (M 1 0 0 0)) (T (T (T l (M 1 0 (- 0 0.5) 0)) (M $0 0 0 0)) (M 1 0 0 (- (* (* 0.5 1) 2) 0))))) $0) (#(lambda (lambda (T (T (T l (M 1 0 (- 0 0.5) 0)) (M $0 0 0 0)) (M 1 0 0 (- (* (* 0.5 1) 2) $1))))) 1 $1)))) (#(- #(* 1 2)) 1) (#(- #(* 1 2)) 0)) (#(lambda (lambda (T (T (T l (M 1 0 (- 0 0.5) 0)) (M $0 0 0 0)) (M 1 0 0 (- (* (* 0.5 1) 2) $1))))) 2 (#(- #(* 1 2)) 2)))"
      ],
      "utility": 150,
      "expected_cost": 3828,
      "final_cost": 3828,
      "multiplier": 1.158307210031348,
      "multiplier_wrt_orig": 26.856844305120166,
      "num_uses": 3,
      "uses": [
        {
          "fn_7 c fn_0": "(fn_1 c (fn_0 (fn_5 0)))"
        },
        {
          "fn_7 c (fn_4 (fn_5 1))": "(fn_1 c (fn_4 (fn_5 1) (fn_5 0)))"
        },
        {
          "fn_7 r fn_0": "(fn_1 r (fn_0 (fn_5 0)))"
        }
      ]
    },
    {
      "body": "(fn_0 fn_3)",
      "dreamcoder": "#(#(lambda (C (T (T (T l (M 3 (/ pi 2) 0 (- 0 2))) (M 1 0 0 0)) (M 1 0 0 0)) (T (T (T l (M 1 0 (- 0 0.5) 0)) (M $0 0 0 0)) (M 1 0 0 (- (* (* 0.5 1) 2) 0))))) #(* 1 2))",
      "arity": 0,
      "name": "fn_8",
      "rewritten": [
        "(fn_7 c fn_0)",
        "(fn_7 r fn_0)",
        "fn_8",
        "(fn_1 c fn_8)",
        "(fn_1 r fn_8)",
        "(fn_7 c (fn_4 (fn_5 1)))",
        "fn_6",
        "(fn_1 c fn_6)",
        "(fn_1 r fn_6)",
        "(C (fn_4 (fn_5 1) (fn_5 0)) (fn_2 2 (fn_5 2)))"
      ],
      "rewritten_dreamcoder": [
        "(#(lambda (lambda (#(lambda (lambda (C (C $0 (T (T $1 (M 1 0 (- 0 (+ 0.5 1)) (* 0.5 1))) (M 1 0 0 (* 0.5 1)))) (T (T $1 (M 1 0 (+ 0.5 1) (* 0.5 1))) (M 1 0 0 (* 0.5 1)))))) $1 ($0 (#(- #(* 1 2)) 0))))) c #(lambda (C (T (T (T l (M 3 (/ pi 2) 0 (- 0 2))) (M 1 0 0 0)) (M 1 0 0 0)) (T (T (T l (M 1 0 (- 0 0.5) 0)) (M $0 0 0 0)) (M 1 0 0 (- (* (* 0.5 1) 2) 0))))))",
        "(#(lambda (lambda (#(lambda (lambda (C (C $0 (T (T $1 (M 1 0 (- 0 (+ 0.5 1)) (* 0.5 1))) (M 1 0 0 (* 0.5 1)))) (T (T $1 (M 1 0 (+ 0.5 1) (* 0.5 1))) (M 1 0 0 (* 0.5 1)))))) $1 ($0 (#(- #(* 1 2)) 0))))) r #(lambda (C (T (T (T l (M 3 (/ pi 2) 0 (- 0 2))) (M 1 0 0 0)) (M 1 0 0 0)) (T (T (T l (M 1 0 (- 0 0.5) 0)) (M $0 0 0 0)) (M 1 0 0 (- (* (* 0.5 1) 2) 0))))))",
        "#(#(lambda (C (T (T (T l (M 3 (/ pi 2) 0 (- 0 2))) (M 1 0 0 0)) (M 1 0 0 0)) (T (T (T l (M 1 0 (- 0 0.5) 0)) (M $0 0 0 0)) (M 1 0 0 (- (* (* 0.5 1) 2) 0))))) #(* 1 2))",
        "(#(lambda (lambda (C (C $0 (T (T $1 (M 1 0 (- 0 (+ 0.5 1)) (* 0.5 1))) (M 1 0 0 (* 0.5 1)))) (T (T $1 (M 1 0 (+ 0.5 1) (* 0.5 1))) (M 1 0 0 (* 0.5 1)))))) c #(#(lambda (C (T (T (T l (M 3 (/ pi 2) 0 (- 0 2))) (M 1 0 0 0)) (M 1 0 0 0)) (T (T (T l (M 1 0 (- 0 0.5) 0)) (M $0 0 0 0)) (M 1 0 0 (- (* (* 0.5 1) 2) 0))))) #(* 1 2)))",
        "(#(lambda (lambda (C (C $0 (T (T $1 (M 1 0 (- 0 (+ 0.5 1)) (* 0.5 1))) (M 1 0 0 (* 0.5 1)))) (T (T $1 (M 1 0 (+ 0.5 1) (* 0.5 1))) (M 1 0 0 (* 0.5 1)))))) r #(#(lambda (C (T (T (T l (M 3 (/ pi 2) 0 (- 0 2))) (M 1 0 0 0)) (M 1 0 0 0)) (T (T (T l (M 1 0 (- 0 0.5) 0)) (M $0 0 0 0)) (M 1 0 0 (- (* (* 0.5 1) 2) 0))))) #(* 1 2)))",
        "(#(lambda (lambda (#(lambda (lambda (C (C $0 (T (T $1 (M 1 0 (- 0 (+ 0.5 1)) (* 0.5 1))) (M 1 0 0 (* 0.5 1)))) (T (T $1 (M 1 0 (+ 0.5 1) (* 0.5 1))) (M 1 0 0 (* 0.5 1)))))) $1 ($0 (#(- #(* 1 2)) 0))))) c (#(lambda (lambda (C (#(lambda (C (T (T (T l (M 3 (/ pi 2) 0 (- 0 2))) (M 1 0 0 0)) (M 1 0 0 0)) (T (T (T l (M 1 0 (- 0 0.5) 0)) (M $0 0 0 0)) (M 1 0 0 (- (* (* 0.5 1) 2) 0))))) $0) (#(lambda (lambda (T (T (T l (M 1 0 (- 0 0.5) 0)) (M $0 0 0 0)) (M 1 0 0 (- (* (* 0.5 1) 2) $1))))) 1 $1)))) (#(- #(* 1 2)) 1)))",
        "#(#(lambda (lambda (C (#(lambda (C (T (T (T l (M 3 (/ pi 2) 0 (- 0 2))) (M 1 0 0 0)) (M 1 0 0 0)) (T (T (T l (M 1 0 (- 0 0.5) 0)) (M $0 0 0 0)) (M 1 0 0 (- (* (* 0.5 1) 2) 0))))) $0) (#(lambda (lambda (T (T (T l (M 1 0 (- 0 0.5) 0)) (M $0 0 0 0)) (M 1 0 0 (- (* (* 0.5 1) 2) $1))))) 1 $1)))) #(* 1 2) #(* 1 2))",
        "(#(lambda (lambda (C (C $0 (T (T $1 (M 1 0 (- 0 (+ 0.5 1)) (* 0.5 1))) (M 1 0 0 (* 0.5 1)))) (T (T $1 (M 1 0 (+ 0.5 1) (* 0.5 1))) (M 1 0 0 (* 0.5 1)))))) c #(#(lambda (lambda (C (#(lambda (C (T (T (T l (M 3 (/ pi 2) 0 (- 0 2))) (M 1 0 0 0)) (M 1 0 0 0)) (T (T (T l (M 1 0 (- 0 0.5) 0)) (M $0 0 0 0)) (M 1 0 0 (- (* (* 0.5 1) 2) 0))))) $0) (#(lambda (lambda (T (T (T l (M 1 0 (- 0 0.5) 0)) (M $0 0 0 0)) (M 1 0 0 (- (* (* 0.5 1) 2) $1))))) 1 $1)))) #(* 1 2) #(* 1 2)))",
        "(#(lambda (lambda (C (C $0 (T (T $1 (M 1 0 (- 0 (+ 0.5 1)) (* 0.5 1))) (M 1 0 0 (* 0.5 1)))) (T (T $1 (M 1 0 (+ 0.5 1) (* 0.5 1))) (M 1 0 0 (* 0.5 1)))))) r #(#(lambda (lambda (C (#(lambda (C (T (T (T l (M 3 (/ pi 2) 0 (- 0 2))) (M 1 0 0 0)) (M 1 0 0 0)) (T (T (T l (M 1 0 (- 0 0.5) 0)) (M $0 0 0 0)) (M 1 0 0 (- (* (* 0.5 1) 2) 0))))) $0) (#(lambda (lambda (T (T (T l (M 1 0 (- 0 0.5) 0)) (M $0 0 0 0)) (M 1 0 0 (- (* (* 0.5 1) 2) $1))))) 1 $1)))) #(* 1 2) #(* 1 2)))",
        "(C (#(lambda (lambda (C (#(lambda (C (T (T (T l (M 3 (/ pi 2) 0 (- 0 2))) (M 1 0 0 0)) (M 1 0 0 0)) (T (T (T l (M 1 0 (- 0 0.5) 0)) (M $0 0 0 0)) (M 1 0 0 (- (* (* 0.5 1) 2) 0))))) $0) (#(lambda (lambda (T (T (T l (M 1 0 (- 0 0.5) 0)) (M $0 0 0 0)) (M 1 0 0 (- (* (* 0.5 1) 2) $1))))) 1 $1)))) (#(- #(* 1 2)) 1) (#(- #(* 1 2)) 0)) (#(lambda (lambda (T (T (T l (M 1 0 (- 0 0.5) 0)) (M $0 0 0 0)) (M 1 0 0 (- (* (* 0.5 1) 2) $1))))) 2 (#(- #(* 1 2)) 2)))"
      ],
      "utility": 2,
      "expected_cost": 3525,
      "final_cost": 3525,
      "multiplier": 1.0859574468085107,
      "multiplier_wrt_orig": 29.165390070921987,
      "num_uses": 3,
      "uses": [
        {
          "fn_8 ": "(fn_0 fn_3)"
        }
      ]
    }
  ]
}